morph_drive/__init__.py
morph_drive/conditions/__init__.py
morph_drive/env/ModularRobotEnv.py
morph_drive/env/__init__.py
morph_drive/policy/__init__.py
morph_drive/policy/do_nothing.py
morph_drive/policy/policy_base.py
morph_drive/policy/random_continuous.py
morph_drive/policy/random_discrete.py
morph_drive/policy/q_learning/__init__.py
morph_drive/policy/q_learning/pitch_roll.py
morph_drive/policy/q_learning/yaw_pitch_roll.py
morph_drive/pre_processors/BasicDataPreprocessor.py
morph_drive/pre_processors/__init__.py
morph_drive/rewards/BasicRewardCalculator.py
morph_drive/rewards/__init__.py
morph_drive/robots/__init__.py
morph_drive/robots/physical_robot.py
morph_drive/robots/serial_communicator.py
morph_drive/robots/simulated_robot.py
morph_drive-0.2.5.dist-info/licenses/LICENSE
morph_drive-0.2.5.dist-info/METADATA
morph_drive-0.2.5.dist-info/WHEEL
morph_drive-0.2.5.dist-info/top_level.txt
morph_drive-0.2.5.dist-info/RECORD
