Metadata-Version: 2.4
Name: morph-drive
Version: 0.2.5
Summary: A package for morph-drive algorithms in origami robotics
Author-email: Nuwan Jaliyagoda <nuwan.jaliyagoda@gmail.com>
Maintainer: Nuwan Jaliyagoda
License-Expression: Apache-2.0
Requires-Python: >=3.13
License-File: LICENSE
Requires-Dist: numpy==2.2.6
Requires-Dist: matplotlib==3.10.3
Requires-Dist: gymnasium==1.1.1
Requires-Dist: gymnasium[mujoco]
Requires-Dist: pyserial==3.5
Dynamic: license-file
